streamlit_redis/__init__.py
streamlit_redis/cache.py
streamlit_redis-0.0.3.dist-info/LICENSE
streamlit_redis-0.0.3.dist-info/METADATA
streamlit_redis-0.0.3.dist-info/WHEEL
streamlit_redis-0.0.3.dist-info/top_level.txt
streamlit_redis-0.0.3.dist-info/RECORD
