Metadata-Version: 2.1
Name: streamlit-redis
Version: 0.0.3
Summary: Redis connector for Streamlit cache
Author-email: Karen Javadyan <kajarenc2@gmail.com>
License: MIT License
Project-URL: Homepage, https://github.com/kajarenc/streamlit-redis
Keywords: streamlit,redis,cache
Classifier: License :: OSI Approved :: MIT License
Classifier: Programming Language :: Python
Classifier: Programming Language :: Python :: 3
Requires-Python: >=3.8
License-File: LICENSE
Requires-Dist: streamlit >=1.27.0
Requires-Dist: redis >=5.0.1
Provides-Extra: dev
Requires-Dist: black ; extra == 'dev'
Requires-Dist: isort ; extra == 'dev'
Requires-Dist: pytest ; extra == 'dev'
Requires-Dist: ipython ; extra == 'dev'
Requires-Dist: memray ; extra == 'dev'
